README.txt
setup.py
AuthRPC/__init__.py
AuthRPC/tests.py
AuthRPC.egg-info/PKG-INFO
AuthRPC.egg-info/SOURCES.txt
AuthRPC.egg-info/dependency_links.txt
AuthRPC.egg-info/requires.txt
AuthRPC.egg-info/top_level.txt
AuthRPC/client/__init__.py
AuthRPC/server/__init__.py