Metadata-Version: 1.0
Name: AuthRPC
Version: 0.3.0a
Summary: A JSONRPC-like client and server with additions to enable authenticated requests
Home-page: http://www.wyre-it.co.uk/authrpc/
Author: Ben Croston
Author-email: ben@croston.org
License: MIT
Keywords: json,rpc,wsgi,auth
Platform: Any
Classifier: Development Status :: 3 - Alpha
Classifier: Operating System :: OS Independent
Classifier: License :: OSI Approved :: MIT License
Classifier: Intended Audience :: Developers
Classifier: Programming Language :: Python :: 2.7
Classifier: Programming Language :: Python :: 3
Classifier: Topic :: Software Development
Classifier: Topic :: Internet :: WWW/HTTP :: WSGI
